vcfvalidator/__init__.py
vcfvalidator/cli.py
vcfvalidator/parser.py
vcfvalidator/result.py
vcfvalidator/vcfvalidator.py
vcfvalidator-1.0.3.dist-info/entry_points.txt
vcfvalidator-1.0.3.dist-info/WHEEL
vcfvalidator-1.0.3.dist-info/METADATA
vcfvalidator-1.0.3.dist-info/RECORD
